embedbase/__init__.py
embedbase/__main__.py
embedbase/api.py
embedbase/app.py
embedbase/database/__init__.py
embedbase/database/base.py
embedbase/database/memory_db.py
embedbase/database/postgres_db.py
embedbase/database/supabase_db.py
embedbase/embedding/__init__.py
embedbase/embedding/base.py
embedbase/embedding/cohere.py
embedbase/embedding/openai.py
embedbase/firebase_auth.py
embedbase/logging_utils.py
embedbase/models.py
embedbase/settings.py
embedbase/strings.py
embedbase/supabase_auth.py
embedbase/utils.py
embedbase-1.2.8.dist-info/LICENSE
embedbase-1.2.8.dist-info/METADATA
embedbase-1.2.8.dist-info/WHEEL
embedbase-1.2.8.dist-info/entry_points.txt
embedbase-1.2.8.dist-info/RECORD
