Metadata-Version: 2.1
Name: embedbase
Version: 1.2.8
Summary: Open-source API & SDK to integrate your data and easily hook them up to LLMs.
Home-page: https://github.com/different-ai/embedbase
License: MIT
Keywords: embeddings,machine learning,artificial intelligence,llm
Author: Different AI
Author-email: louis@embedbase.xyz
Requires-Python: >=3.8,<4.0
Classifier: Development Status :: 4 - Beta
Classifier: Intended Audience :: Developers
Classifier: License :: OSI Approved :: MIT License
Classifier: Programming Language :: Python :: 3
Classifier: Programming Language :: Python :: 3.8
Classifier: Programming Language :: Python :: 3.9
Classifier: Programming Language :: Python :: 3.10
Classifier: Programming Language :: Python :: 3.11
Classifier: Programming Language :: Python :: 3
Classifier: Programming Language :: Python :: 3.10
Classifier: Programming Language :: Python :: 3.8
Classifier: Programming Language :: Python :: 3.9
Classifier: Topic :: Scientific/Engineering :: Artificial Intelligence
Requires-Dist: fastapi (>=0.95.1,<0.96.0)
Requires-Dist: openai (>=0.27.0,<0.28.0)
Requires-Dist: pandas (>=1.3.4,<2.0.0)
Requires-Dist: pydantic_yaml[pyyaml] (>=0.4.0,<0.5.0)
Requires-Dist: tenacity (>=8.0.1,<9.0.0)
Requires-Dist: tiktoken (>=0.3.3,<0.4.0)
Requires-Dist: uvicorn[standard] (>=0.22.0,<0.23.0)
Project-URL: Repository, https://github.com/different-ai/embedbase
